mruclml/__init__.py
mruclml-0.1.0.dist-info/licenses/LICENSE
mruclml-0.1.0.dist-info/WHEEL
mruclml-0.1.0.dist-info/METADATA
mruclml-0.1.0.dist-info/RECORD
